atriegc.cpython-37m-x86_64-linux-gnu.so
atriegc-0.0.4.dist-info/LICENSE
atriegc-0.0.4.dist-info/METADATA
atriegc-0.0.4.dist-info/top_level.txt
atriegc-0.0.4.dist-info/RECORD
atriegc-0.0.4.dist-info/WHEEL
