Metadata-Version: 2.1
Name: atriegc
Version: 0.0.4
Summary: A module using prefix trees to store/search nucleotides sequences
Home-page: https://github.com/statbiophys/ATrieGC
Author: Thomas Dupic
Author-email: dupic.thomas@gmail.com
License: UNKNOWN
Platform: UNKNOWN
Classifier: Development Status :: 1 - Planning
Classifier: Intended Audience :: Science/Research
Classifier: License :: OSI Approved :: BSD License
Classifier: Operating System :: POSIX :: Linux
Classifier: Programming Language :: Python :: 3.4
Classifier: Programming Language :: Python :: 3.5
License-File: LICENSE
